forumscraper/__init__.py
forumscraper/__main__.py
forumscraper/args.py
forumscraper/defs.py
forumscraper/exceptions.py
forumscraper/utils.py
forumscraper/extractors/common.py
forumscraper/extractors/extractor.py
forumscraper/extractors/hackernews.py
forumscraper/extractors/identify.py
forumscraper/extractors/invision.py
forumscraper/extractors/phpbb.py
forumscraper/extractors/smf.py
forumscraper/extractors/stackexchange.py
forumscraper/extractors/vbulletin.py
forumscraper/extractors/xenforo.py
forumscraper/extractors/xmb.py
forumscraper/reliq/hackernews/comments.reliq
forumscraper/reliq/hackernews/post.reliq
forumscraper/reliq/hackernews/user.reliq
forumscraper/reliq/invision/findroot.reliq
forumscraper/reliq/invision/forum.reliq
forumscraper/reliq/invision/post-reactions.reliq
forumscraper/reliq/invision/post.reliq
forumscraper/reliq/invision/reactions.reliq
forumscraper/reliq/invision/thread-recommended.reliq
forumscraper/reliq/invision/thread.reliq
forumscraper/reliq/invision/user.reliq
forumscraper/reliq/phpbb/findroot.reliq
forumscraper/reliq/phpbb/forum.reliq
forumscraper/reliq/phpbb/posts.reliq
forumscraper/reliq/phpbb/thread.reliq
forumscraper/reliq/smf1/findroot.reliq
forumscraper/reliq/smf1/forum.reliq
forumscraper/reliq/smf1/posts.reliq
forumscraper/reliq/smf1/thread.reliq
forumscraper/reliq/smf2/findroot.reliq
forumscraper/reliq/smf2/forum.reliq
forumscraper/reliq/smf2/posts.reliq
forumscraper/reliq/stackexchange/forum.reliq
forumscraper/reliq/stackexchange/post-comments.reliq
forumscraper/reliq/stackexchange/post.reliq
forumscraper/reliq/stackexchange/thread.reliq
forumscraper/reliq/stackexchange/user.reliq
forumscraper/reliq/vbulletin/findroot.reliq
forumscraper/reliq/vbulletin/forum-threads.reliq
forumscraper/reliq/vbulletin/forum.reliq
forumscraper/reliq/vbulletin/next-page.reliq
forumscraper/reliq/vbulletin/posts.reliq
forumscraper/reliq/vbulletin/thread.reliq
forumscraper/reliq/xenforo1/findroot.reliq
forumscraper/reliq/xenforo1/forum.reliq
forumscraper-0.1.21.dist-info/licenses/LICENSE
forumscraper-0.1.21.dist-info/METADATA
forumscraper-0.1.21.dist-info/WHEEL
forumscraper-0.1.21.dist-info/entry_points.txt
forumscraper-0.1.21.dist-info/top_level.txt
forumscraper-0.1.21.dist-info/RECORD
